<?xml version="1.0" encoding="UTF-8"?>
<routes>
	<route cost="48426.754931076895" cities="21" team="Tonathiu">
		<city name="campo base" id="0">
		</city>
		<city name="Guapalupa" id="8">
		</city>
		<city name="Cusco" id="6">
		</city>
		<city name="Verolanuova" id="15">
		</city>
		<city name="Verolanuova" id="26">
		</city>
		<city name="Qu'umarkaj" id="40">
		</city>
		<city name="Verolanuova" id="54">
		</city>
		<city name="Guaia" id="63">
		</city>
		<city name="Chiqua" id="67">
		</city>
		<city name="Teotiguacan" id="80">
		</city>
		<city name="Quirigua" id="84">
		</city>
		<city name="Guaia" id="93">
		</city>
		<city name="Teotiguacan" id="103">
		</city>
		<city name="Tikal" id="113">
		</city>
		<city name="Cusco" id="122">
		</city>
		<city name="Rio" id="135">
		</city>
		<city name="Cusco" id="149">
		</city>
		<city name="El Mirador" id="162">
		</city>
		<city name="Macondo" id="176">
		</city>
		<city name="El Mirador" id="186">
		</city>
		<city name="Rovine Perdute" id="199">
		</city>
	</route>
	<route cost="7449.0" cities="24" team="Metztli">
		<city name="campo base" id="0">
		</city>
		<city name="Quetzacoatl" id="10">
		</city>
		<city name="Rio" id="24">
		</city>
		<city name="Cusco" id="23">
		</city>
		<city name="Quirigua" id="36">
		</city>
		<city name="Quirigua" id="49">
		</city>
		<city name="Chiva" id="56">
		</city>
		<city name="Guaia" id="63">
		</city>
		<city name="Kopa" id="72">
		</city>
		<city name="Guaia" id="76">
		</city>
		<city name="Caracol" id="90">
		</city>
		<city name="Tikal" id="97">
		</city>
		<city name="El Mirador" id="106">
		</city>
		<city name="El Mirador" id="115">
		</city>
		<city name="Chiva" id="127">
		</city>
		<city name="Verolanuova" id="129">
		</city>
		<city name="Chiva" id="140">
		</city>
		<city name="Machu Picchu" id="146">
		</city>
		<city name="El Mirador" id="158">
		</city>
		<city name="Qu'umarkaj" id="172">
		</city>
		<city name="Quetzacoatl" id="185">
		</city>
		<city name="Tikal" id="183">
		</city>
		<city name="Chiva" id="194">
		</city>
		<city name="Rovine Perdute" id="199">
		</city>
	</route>
</routes>
